<NLP-document>
    <text id="0">Наступила зима. Падают крупные снежинки. Кружит ветер. Бежит по земле поземка. Все покрыл пушистый снег.</text>
    <annotations class="java.util.ArrayList">
        <I-annotation confidence="1.0" class="ru.ispras.texterra.core.nlp.datamodel.pos.POSToken">
            <start>0</start>
            <end>9</end>
            <annotated-text reference="0"/>
            <value class="ru.ispras.texterra.core.nlp.datamodel.pos.morph.MorphProperties">
                <pos-tag class="ru.ispras.texterra.core.nlp.datamodel.pos.ruscorpora.RuscorporaPOSTag">V</pos-tag>
                <characters class="java.util.ArrayList">
                    <I-morph-character class="ru.ispras.texterra.core.nlp.datamodel.pos.morph.characters.Gender">Feminine</I-morph-character>
                    <I-morph-character class="ru.ispras.texterra.core.nlp.datamodel.pos.morph.characters.Mode">Indicative</I-morph-character>
                    <I-morph-character class="ru.ispras.texterra.core.nlp.datamodel.pos.morph.characters.Number">Singular</I-morph-character>
                    <I-morph-character class="ru.ispras.texterra.core.nlp.datamodel.pos.morph.characters.Tense">Past</I-morph-character>
                </characters>
            </value>
        </I-annotation>
        <I-annotation confidence="1.0" class="ru.ispras.texterra.core.nlp.datamodel.pos.POSToken">
            <start>10</start>
            <end>14</end>
            <annotated-text reference="0"/>
            <value class="ru.ispras.texterra.core.nlp.datamodel.pos.morph.MorphProperties">
                <pos-tag class="ru.ispras.texterra.core.nlp.datamodel.pos.ruscorpora.RuscorporaPOSTag">S</pos-tag>
                <characters class="java.util.ArrayList">
                    <I-morph-character class="ru.ispras.texterra.core.nlp.datamodel.pos.morph.characters.Case">Nominative</I-morph-character>
                    <I-morph-character class="ru.ispras.texterra.core.nlp.datamodel.pos.morph.characters.Gender">Feminine</I-morph-character>
                    <I-morph-character class="ru.ispras.texterra.core.nlp.datamodel.pos.morph.characters.Number">Singular</I-morph-character>
                </characters>
            </value>
        </I-annotation>
        <I-annotation confidence="1.0" class="ru.ispras.texterra.core.nlp.datamodel.pos.POSToken">
            <start>14</start>
            <end>15</end>
            <annotated-text reference="0"/>
            <value class="ru.ispras.texterra.core.nlp.datamodel.pos.morph.MorphProperties">
                <pos-tag class="ru.ispras.texterra.core.nlp.datamodel.pos.ruscorpora.RuscorporaPOSTag">PUNCT</pos-tag>
                <characters class="java.util.ArrayList"/>
            </value>
        </I-annotation>
        <I-annotation confidence="1.0" class="ru.ispras.texterra.core.nlp.datamodel.pos.POSToken">
            <start>16</start>
            <end>22</end>
            <annotated-text reference="0"/>
            <value class="ru.ispras.texterra.core.nlp.datamodel.pos.morph.MorphProperties">
                <pos-tag class="ru.ispras.texterra.core.nlp.datamodel.pos.ruscorpora.RuscorporaPOSTag">V</pos-tag>
                <characters class="java.util.ArrayList">
                    <I-morph-character class="ru.ispras.texterra.core.nlp.datamodel.pos.morph.characters.Mode">Indicative</I-morph-character>
                    <I-morph-character class="ru.ispras.texterra.core.nlp.datamodel.pos.morph.characters.Number">Plural</I-morph-character>
                    <I-morph-character class="ru.ispras.texterra.core.nlp.datamodel.pos.morph.characters.Person">Third</I-morph-character>
                    <I-morph-character class="ru.ispras.texterra.core.nlp.datamodel.pos.morph.characters.Tense">NotPast</I-morph-character>
                </characters>
            </value>
        </I-annotation>
        <I-annotation confidence="1.0" class="ru.ispras.texterra.core.nlp.datamodel.pos.POSToken">
            <start>23</start>
            <end>30</end>
            <annotated-text reference="0"/>
            <value class="ru.ispras.texterra.core.nlp.datamodel.pos.morph.MorphProperties">
                <pos-tag class="ru.ispras.texterra.core.nlp.datamodel.pos.ruscorpora.RuscorporaPOSTag">A</pos-tag>
                <characters class="java.util.ArrayList">
                    <I-morph-character class="ru.ispras.texterra.core.nlp.datamodel.pos.morph.characters.Case">Nominative</I-morph-character>
                    <I-morph-character class="ru.ispras.texterra.core.nlp.datamodel.pos.morph.characters.Number">Plural</I-morph-character>
                </characters>
            </value>
        </I-annotation>
        <I-annotation confidence="1.0" class="ru.ispras.texterra.core.nlp.datamodel.pos.POSToken">
            <start>31</start>
            <end>39</end>
            <annotated-text reference="0"/>
            <value class="ru.ispras.texterra.core.nlp.datamodel.pos.morph.MorphProperties">
                <pos-tag class="ru.ispras.texterra.core.nlp.datamodel.pos.ruscorpora.RuscorporaPOSTag">S</pos-tag>
                <characters class="java.util.ArrayList">
                    <I-morph-character class="ru.ispras.texterra.core.nlp.datamodel.pos.morph.characters.Case">Nominative</I-morph-character>
                    <I-morph-character class="ru.ispras.texterra.core.nlp.datamodel.pos.morph.characters.Gender">Feminine</I-morph-character>
                    <I-morph-character class="ru.ispras.texterra.core.nlp.datamodel.pos.morph.characters.Number">Plural</I-morph-character>
                </characters>
            </value>
        </I-annotation>
        <I-annotation confidence="1.0" class="ru.ispras.texterra.core.nlp.datamodel.pos.POSToken">
            <start>39</start>
            <end>40</end>
            <annotated-text reference="0"/>
            <value class="ru.ispras.texterra.core.nlp.datamodel.pos.morph.MorphProperties">
                <pos-tag class="ru.ispras.texterra.core.nlp.datamodel.pos.ruscorpora.RuscorporaPOSTag">PUNCT</pos-tag>
                <characters class="java.util.ArrayList"/>
            </value>
        </I-annotation>
        <I-annotation confidence="1.0" class="ru.ispras.texterra.core.nlp.datamodel.pos.POSToken">
            <start>41</start>
            <end>47</end>
            <annotated-text reference="0"/>
            <value class="ru.ispras.texterra.core.nlp.datamodel.pos.morph.MorphProperties">
                <pos-tag class="ru.ispras.texterra.core.nlp.datamodel.pos.ruscorpora.RuscorporaPOSTag">V</pos-tag>
                <characters class="java.util.ArrayList">
                    <I-morph-character class="ru.ispras.texterra.core.nlp.datamodel.pos.morph.characters.Mode">Indicative</I-morph-character>
                    <I-morph-character class="ru.ispras.texterra.core.nlp.datamodel.pos.morph.characters.Number">Singular</I-morph-character>
                    <I-morph-character class="ru.ispras.texterra.core.nlp.datamodel.pos.morph.characters.Person">Third</I-morph-character>
                    <I-morph-character class="ru.ispras.texterra.core.nlp.datamodel.pos.morph.characters.Tense">NotPast</I-morph-character>
                </characters>
            </value>
        </I-annotation>
        <I-annotation confidence="1.0" class="ru.ispras.texterra.core.nlp.datamodel.pos.POSToken">
            <start>48</start>
            <end>53</end>
            <annotated-text reference="0"/>
            <value class="ru.ispras.texterra.core.nlp.datamodel.pos.morph.MorphProperties">
                <pos-tag class="ru.ispras.texterra.core.nlp.datamodel.pos.ruscorpora.RuscorporaPOSTag">S</pos-tag>
                <characters class="java.util.ArrayList">
                    <I-morph-character class="ru.ispras.texterra.core.nlp.datamodel.pos.morph.characters.Case">Nominative</I-morph-character>
                    <I-morph-character class="ru.ispras.texterra.core.nlp.datamodel.pos.morph.characters.Gender">Masculine</I-morph-character>
                    <I-morph-character class="ru.ispras.texterra.core.nlp.datamodel.pos.morph.characters.Number">Singular</I-morph-character>
                </characters>
            </value>
        </I-annotation>
        <I-annotation confidence="1.0" class="ru.ispras.texterra.core.nlp.datamodel.pos.POSToken">
            <start>53</start>
            <end>54</end>
            <annotated-text reference="0"/>
            <value class="ru.ispras.texterra.core.nlp.datamodel.pos.morph.MorphProperties">
                <pos-tag class="ru.ispras.texterra.core.nlp.datamodel.pos.ruscorpora.RuscorporaPOSTag">PUNCT</pos-tag>
                <characters class="java.util.ArrayList"/>
            </value>
        </I-annotation>
        <I-annotation confidence="1.0" class="ru.ispras.texterra.core.nlp.datamodel.pos.POSToken">
            <start>55</start>
            <end>60</end>
            <annotated-text reference="0"/>
            <value class="ru.ispras.texterra.core.nlp.datamodel.pos.morph.MorphProperties">
                <pos-tag class="ru.ispras.texterra.core.nlp.datamodel.pos.ruscorpora.RuscorporaPOSTag">V</pos-tag>
                <characters class="java.util.ArrayList">
                    <I-morph-character class="ru.ispras.texterra.core.nlp.datamodel.pos.morph.characters.Mode">Indicative</I-morph-character>
                    <I-morph-character class="ru.ispras.texterra.core.nlp.datamodel.pos.morph.characters.Number">Singular</I-morph-character>
                    <I-morph-character class="ru.ispras.texterra.core.nlp.datamodel.pos.morph.characters.Person">Third</I-morph-character>
                    <I-morph-character class="ru.ispras.texterra.core.nlp.datamodel.pos.morph.characters.Tense">NotPast</I-morph-character>
                </characters>
            </value>
        </I-annotation>
        <I-annotation confidence="1.0" class="ru.ispras.texterra.core.nlp.datamodel.pos.POSToken">
            <start>61</start>
            <end>63</end>
            <annotated-text reference="0"/>
            <value class="ru.ispras.texterra.core.nlp.datamodel.pos.morph.MorphProperties">
                <pos-tag class="ru.ispras.texterra.core.nlp.datamodel.pos.ruscorpora.RuscorporaPOSTag">PR</pos-tag>
                <characters class="java.util.ArrayList"/>
            </value>
        </I-annotation>
        <I-annotation confidence="1.0" class="ru.ispras.texterra.core.nlp.datamodel.pos.POSToken">
            <start>64</start>
            <end>69</end>
            <annotated-text reference="0"/>
            <value class="ru.ispras.texterra.core.nlp.datamodel.pos.morph.MorphProperties">
                <pos-tag class="ru.ispras.texterra.core.nlp.datamodel.pos.ruscorpora.RuscorporaPOSTag">S</pos-tag>
                <characters class="java.util.ArrayList">
                    <I-morph-character class="ru.ispras.texterra.core.nlp.datamodel.pos.morph.characters.Case">Dative</I-morph-character>
                    <I-morph-character class="ru.ispras.texterra.core.nlp.datamodel.pos.morph.characters.Gender">Feminine</I-morph-character>
                    <I-morph-character class="ru.ispras.texterra.core.nlp.datamodel.pos.morph.characters.Number">Singular</I-morph-character>
                </characters>
            </value>
        </I-annotation>
        <I-annotation confidence="1.0" class="ru.ispras.texterra.core.nlp.datamodel.pos.POSToken">
            <start>70</start>
            <end>77</end>
            <annotated-text reference="0"/>
            <value class="ru.ispras.texterra.core.nlp.datamodel.pos.morph.MorphProperties">
                <pos-tag class="ru.ispras.texterra.core.nlp.datamodel.pos.ruscorpora.RuscorporaPOSTag">S</pos-tag>
                <characters class="java.util.ArrayList">
                    <I-morph-character class="ru.ispras.texterra.core.nlp.datamodel.pos.morph.characters.Case">Nominative</I-morph-character>
                    <I-morph-character class="ru.ispras.texterra.core.nlp.datamodel.pos.morph.characters.Gender">Feminine</I-morph-character>
                    <I-morph-character class="ru.ispras.texterra.core.nlp.datamodel.pos.morph.characters.Number">Singular</I-morph-character>
                </characters>
            </value>
        </I-annotation>
        <I-annotation confidence="1.0" class="ru.ispras.texterra.core.nlp.datamodel.pos.POSToken">
            <start>77</start>
            <end>78</end>
            <annotated-text reference="0"/>
            <value class="ru.ispras.texterra.core.nlp.datamodel.pos.morph.MorphProperties">
                <pos-tag class="ru.ispras.texterra.core.nlp.datamodel.pos.ruscorpora.RuscorporaPOSTag">PUNCT</pos-tag>
                <characters class="java.util.ArrayList"/>
            </value>
        </I-annotation>
        <I-annotation confidence="1.0" class="ru.ispras.texterra.core.nlp.datamodel.pos.POSToken">
            <start>79</start>
            <end>82</end>
            <annotated-text reference="0"/>
            <value class="ru.ispras.texterra.core.nlp.datamodel.pos.morph.MorphProperties">
                <pos-tag class="ru.ispras.texterra.core.nlp.datamodel.pos.ruscorpora.RuscorporaPOSTag">A</pos-tag>
                <characters class="java.util.ArrayList">
                    <I-morph-character class="ru.ispras.texterra.core.nlp.datamodel.pos.morph.characters.Case">Nominative</I-morph-character>
                    <I-morph-character class="ru.ispras.texterra.core.nlp.datamodel.pos.morph.characters.Number">Plural</I-morph-character>
                </characters>
            </value>
        </I-annotation>
        <I-annotation confidence="1.0" class="ru.ispras.texterra.core.nlp.datamodel.pos.POSToken">
            <start>83</start>
            <end>89</end>
            <annotated-text reference="0"/>
            <value class="ru.ispras.texterra.core.nlp.datamodel.pos.morph.MorphProperties">
                <pos-tag class="ru.ispras.texterra.core.nlp.datamodel.pos.ruscorpora.RuscorporaPOSTag">V</pos-tag>
                <characters class="java.util.ArrayList">
                    <I-morph-character class="ru.ispras.texterra.core.nlp.datamodel.pos.morph.characters.Gender">Masculine</I-morph-character>
                    <I-morph-character class="ru.ispras.texterra.core.nlp.datamodel.pos.morph.characters.Mode">Indicative</I-morph-character>
                    <I-morph-character class="ru.ispras.texterra.core.nlp.datamodel.pos.morph.characters.Number">Singular</I-morph-character>
                    <I-morph-character class="ru.ispras.texterra.core.nlp.datamodel.pos.morph.characters.Tense">Past</I-morph-character>
                </characters>
            </value>
        </I-annotation>
        <I-annotation confidence="1.0" class="ru.ispras.texterra.core.nlp.datamodel.pos.POSToken">
            <start>90</start>
            <end>98</end>
            <annotated-text reference="0"/>
            <value class="ru.ispras.texterra.core.nlp.datamodel.pos.morph.MorphProperties">
                <pos-tag class="ru.ispras.texterra.core.nlp.datamodel.pos.ruscorpora.RuscorporaPOSTag">A</pos-tag>
                <characters class="java.util.ArrayList">
                    <I-morph-character class="ru.ispras.texterra.core.nlp.datamodel.pos.morph.characters.Case">Nominative</I-morph-character>
                    <I-morph-character class="ru.ispras.texterra.core.nlp.datamodel.pos.morph.characters.Gender">Masculine</I-morph-character>
                    <I-morph-character class="ru.ispras.texterra.core.nlp.datamodel.pos.morph.characters.Number">Singular</I-morph-character>
                </characters>
            </value>
        </I-annotation>
        <I-annotation confidence="1.0" class="ru.ispras.texterra.core.nlp.datamodel.pos.POSToken">
            <start>99</start>
            <end>103</end>
            <annotated-text reference="0"/>
            <value class="ru.ispras.texterra.core.nlp.datamodel.pos.morph.MorphProperties">
                <pos-tag class="ru.ispras.texterra.core.nlp.datamodel.pos.ruscorpora.RuscorporaPOSTag">S</pos-tag>
                <characters class="java.util.ArrayList">
                    <I-morph-character class="ru.ispras.texterra.core.nlp.datamodel.pos.morph.characters.Case">Nominative</I-morph-character>
                    <I-morph-character class="ru.ispras.texterra.core.nlp.datamodel.pos.morph.characters.Gender">Masculine</I-morph-character>
                    <I-morph-character class="ru.ispras.texterra.core.nlp.datamodel.pos.morph.characters.Number">Singular</I-morph-character>
                </characters>
            </value>
        </I-annotation>
        <I-annotation confidence="1.0" class="ru.ispras.texterra.core.nlp.datamodel.pos.POSToken">
            <start>103</start>
            <end>104</end>
            <annotated-text reference="0"/>
            <value class="ru.ispras.texterra.core.nlp.datamodel.pos.morph.MorphProperties">
                <pos-tag class="ru.ispras.texterra.core.nlp.datamodel.pos.ruscorpora.RuscorporaPOSTag">PUNCT</pos-tag>
                <characters class="java.util.ArrayList"/>
            </value>
        </I-annotation>
    </annotations>
</NLP-document>