<NLP-document>
    <text id="0">Коля позвал овчарку Дуську. Они отправились на площадку. Дуська выполняла команды. А мальчик угощал её сахаром</text>
    <annotations class="java.util.ArrayList">
        <I-annotation confidence="1.0" class="ru.ispras.texterra.core.nlp.datamodel.pos.POSToken">
            <start>0</start>
            <end>4</end>
            <annotated-text reference="0"/>
            <value class="ru.ispras.texterra.core.nlp.datamodel.pos.morph.MorphProperties">
                <pos-tag class="ru.ispras.texterra.core.nlp.datamodel.pos.ruscorpora.RuscorporaPOSTag">S</pos-tag>
                <characters class="java.util.ArrayList">
                    <I-morph-character class="ru.ispras.texterra.core.nlp.datamodel.pos.morph.characters.Case">Nominative</I-morph-character>
                    <I-morph-character class="ru.ispras.texterra.core.nlp.datamodel.pos.morph.characters.Gender">Feminine</I-morph-character>
                    <I-morph-character class="ru.ispras.texterra.core.nlp.datamodel.pos.morph.characters.Number">Singular</I-morph-character>
                </characters>
            </value>
        </I-annotation>
        <I-annotation confidence="1.0" class="ru.ispras.texterra.core.nlp.datamodel.pos.POSToken">
            <start>5</start>
            <end>11</end>
            <annotated-text reference="0"/>
            <value class="ru.ispras.texterra.core.nlp.datamodel.pos.morph.MorphProperties">
                <pos-tag class="ru.ispras.texterra.core.nlp.datamodel.pos.ruscorpora.RuscorporaPOSTag">V</pos-tag>
                <characters class="java.util.ArrayList">
                    <I-morph-character class="ru.ispras.texterra.core.nlp.datamodel.pos.morph.characters.Mode">Indicative</I-morph-character>
                    <I-morph-character class="ru.ispras.texterra.core.nlp.datamodel.pos.morph.characters.Number">Singular</I-morph-character>
                    <I-morph-character class="ru.ispras.texterra.core.nlp.datamodel.pos.morph.characters.Person">Third</I-morph-character>
                    <I-morph-character class="ru.ispras.texterra.core.nlp.datamodel.pos.morph.characters.Tense">NotPast</I-morph-character>
                </characters>
            </value>
        </I-annotation>
        <I-annotation confidence="1.0" class="ru.ispras.texterra.core.nlp.datamodel.pos.POSToken">
            <start>12</start>
            <end>19</end>
            <annotated-text reference="0"/>
            <value class="ru.ispras.texterra.core.nlp.datamodel.pos.morph.MorphProperties">
                <pos-tag class="ru.ispras.texterra.core.nlp.datamodel.pos.ruscorpora.RuscorporaPOSTag">S</pos-tag>
                <characters class="java.util.ArrayList">
                    <I-morph-character class="ru.ispras.texterra.core.nlp.datamodel.pos.morph.characters.Case">Accusative</I-morph-character>
                    <I-morph-character class="ru.ispras.texterra.core.nlp.datamodel.pos.morph.characters.Gender">Feminine</I-morph-character>
                    <I-morph-character class="ru.ispras.texterra.core.nlp.datamodel.pos.morph.characters.Number">Singular</I-morph-character>
                </characters>
            </value>
        </I-annotation>
        <I-annotation confidence="1.0" class="ru.ispras.texterra.core.nlp.datamodel.pos.POSToken">
            <start>20</start>
            <end>26</end>
            <annotated-text reference="0"/>
            <value class="ru.ispras.texterra.core.nlp.datamodel.pos.morph.MorphProperties">
                <pos-tag class="ru.ispras.texterra.core.nlp.datamodel.pos.ruscorpora.RuscorporaPOSTag">S</pos-tag>
                <characters class="java.util.ArrayList">
                    <I-morph-character class="ru.ispras.texterra.core.nlp.datamodel.pos.morph.characters.Case">Accusative</I-morph-character>
                    <I-morph-character class="ru.ispras.texterra.core.nlp.datamodel.pos.morph.characters.Gender">Feminine</I-morph-character>
                    <I-morph-character class="ru.ispras.texterra.core.nlp.datamodel.pos.morph.characters.Number">Singular</I-morph-character>
                </characters>
            </value>
        </I-annotation>
        <I-annotation confidence="1.0" class="ru.ispras.texterra.core.nlp.datamodel.pos.POSToken">
            <start>26</start>
            <end>27</end>
            <annotated-text reference="0"/>
            <value class="ru.ispras.texterra.core.nlp.datamodel.pos.morph.MorphProperties">
                <pos-tag class="ru.ispras.texterra.core.nlp.datamodel.pos.ruscorpora.RuscorporaPOSTag">PUNCT</pos-tag>
                <characters class="java.util.ArrayList"/>
            </value>
        </I-annotation>
        <I-annotation confidence="1.0" class="ru.ispras.texterra.core.nlp.datamodel.pos.POSToken">
            <start>28</start>
            <end>31</end>
            <annotated-text reference="0"/>
            <value class="ru.ispras.texterra.core.nlp.datamodel.pos.morph.MorphProperties">
                <pos-tag class="ru.ispras.texterra.core.nlp.datamodel.pos.ruscorpora.RuscorporaPOSTag">S</pos-tag>
                <characters class="java.util.ArrayList">
                    <I-morph-character class="ru.ispras.texterra.core.nlp.datamodel.pos.morph.characters.Case">Nominative</I-morph-character>
                    <I-morph-character class="ru.ispras.texterra.core.nlp.datamodel.pos.morph.characters.Number">Plural</I-morph-character>
                </characters>
            </value>
        </I-annotation>
        <I-annotation confidence="1.0" class="ru.ispras.texterra.core.nlp.datamodel.pos.POSToken">
            <start>32</start>
            <end>43</end>
            <annotated-text reference="0"/>
            <value class="ru.ispras.texterra.core.nlp.datamodel.pos.morph.MorphProperties">
                <pos-tag class="ru.ispras.texterra.core.nlp.datamodel.pos.ruscorpora.RuscorporaPOSTag">V</pos-tag>
                <characters class="java.util.ArrayList">
                    <I-morph-character class="ru.ispras.texterra.core.nlp.datamodel.pos.morph.characters.Mode">Indicative</I-morph-character>
                    <I-morph-character class="ru.ispras.texterra.core.nlp.datamodel.pos.morph.characters.Number">Plural</I-morph-character>
                    <I-morph-character class="ru.ispras.texterra.core.nlp.datamodel.pos.morph.characters.Tense">Past</I-morph-character>
                </characters>
            </value>
        </I-annotation>
        <I-annotation confidence="1.0" class="ru.ispras.texterra.core.nlp.datamodel.pos.POSToken">
            <start>44</start>
            <end>46</end>
            <annotated-text reference="0"/>
            <value class="ru.ispras.texterra.core.nlp.datamodel.pos.morph.MorphProperties">
                <pos-tag class="ru.ispras.texterra.core.nlp.datamodel.pos.ruscorpora.RuscorporaPOSTag">PR</pos-tag>
                <characters class="java.util.ArrayList"/>
            </value>
        </I-annotation>
        <I-annotation confidence="1.0" class="ru.ispras.texterra.core.nlp.datamodel.pos.POSToken">
            <start>47</start>
            <end>55</end>
            <annotated-text reference="0"/>
            <value class="ru.ispras.texterra.core.nlp.datamodel.pos.morph.MorphProperties">
                <pos-tag class="ru.ispras.texterra.core.nlp.datamodel.pos.ruscorpora.RuscorporaPOSTag">S</pos-tag>
                <characters class="java.util.ArrayList">
                    <I-morph-character class="ru.ispras.texterra.core.nlp.datamodel.pos.morph.characters.Case">Accusative</I-morph-character>
                    <I-morph-character class="ru.ispras.texterra.core.nlp.datamodel.pos.morph.characters.Gender">Feminine</I-morph-character>
                    <I-morph-character class="ru.ispras.texterra.core.nlp.datamodel.pos.morph.characters.Number">Singular</I-morph-character>
                </characters>
            </value>
        </I-annotation>
        <I-annotation confidence="1.0" class="ru.ispras.texterra.core.nlp.datamodel.pos.POSToken">
            <start>55</start>
            <end>56</end>
            <annotated-text reference="0"/>
            <value class="ru.ispras.texterra.core.nlp.datamodel.pos.morph.MorphProperties">
                <pos-tag class="ru.ispras.texterra.core.nlp.datamodel.pos.ruscorpora.RuscorporaPOSTag">PUNCT</pos-tag>
                <characters class="java.util.ArrayList"/>
            </value>
        </I-annotation>
        <I-annotation confidence="1.0" class="ru.ispras.texterra.core.nlp.datamodel.pos.POSToken">
            <start>57</start>
            <end>63</end>
            <annotated-text reference="0"/>
            <value class="ru.ispras.texterra.core.nlp.datamodel.pos.morph.MorphProperties">
                <pos-tag class="ru.ispras.texterra.core.nlp.datamodel.pos.ruscorpora.RuscorporaPOSTag">S</pos-tag>
                <characters class="java.util.ArrayList">
                    <I-morph-character class="ru.ispras.texterra.core.nlp.datamodel.pos.morph.characters.Case">Nominative</I-morph-character>
                    <I-morph-character class="ru.ispras.texterra.core.nlp.datamodel.pos.morph.characters.Gender">Feminine</I-morph-character>
                    <I-morph-character class="ru.ispras.texterra.core.nlp.datamodel.pos.morph.characters.Number">Singular</I-morph-character>
                </characters>
            </value>
        </I-annotation>
        <I-annotation confidence="1.0" class="ru.ispras.texterra.core.nlp.datamodel.pos.POSToken">
            <start>64</start>
            <end>73</end>
            <annotated-text reference="0"/>
            <value class="ru.ispras.texterra.core.nlp.datamodel.pos.morph.MorphProperties">
                <pos-tag class="ru.ispras.texterra.core.nlp.datamodel.pos.ruscorpora.RuscorporaPOSTag">V</pos-tag>
                <characters class="java.util.ArrayList">
                    <I-morph-character class="ru.ispras.texterra.core.nlp.datamodel.pos.morph.characters.Gender">Feminine</I-morph-character>
                    <I-morph-character class="ru.ispras.texterra.core.nlp.datamodel.pos.morph.characters.Mode">Indicative</I-morph-character>
                    <I-morph-character class="ru.ispras.texterra.core.nlp.datamodel.pos.morph.characters.Number">Singular</I-morph-character>
                    <I-morph-character class="ru.ispras.texterra.core.nlp.datamodel.pos.morph.characters.Tense">Past</I-morph-character>
                </characters>
            </value>
        </I-annotation>
        <I-annotation confidence="1.0" class="ru.ispras.texterra.core.nlp.datamodel.pos.POSToken">
            <start>74</start>
            <end>81</end>
            <annotated-text reference="0"/>
            <value class="ru.ispras.texterra.core.nlp.datamodel.pos.morph.MorphProperties">
                <pos-tag class="ru.ispras.texterra.core.nlp.datamodel.pos.ruscorpora.RuscorporaPOSTag">S</pos-tag>
                <characters class="java.util.ArrayList">
                    <I-morph-character class="ru.ispras.texterra.core.nlp.datamodel.pos.morph.characters.Case">Nominative</I-morph-character>
                    <I-morph-character class="ru.ispras.texterra.core.nlp.datamodel.pos.morph.characters.Gender">Feminine</I-morph-character>
                    <I-morph-character class="ru.ispras.texterra.core.nlp.datamodel.pos.morph.characters.Number">Plural</I-morph-character>
                </characters>
            </value>
        </I-annotation>
        <I-annotation confidence="1.0" class="ru.ispras.texterra.core.nlp.datamodel.pos.POSToken">
            <start>81</start>
            <end>82</end>
            <annotated-text reference="0"/>
            <value class="ru.ispras.texterra.core.nlp.datamodel.pos.morph.MorphProperties">
                <pos-tag class="ru.ispras.texterra.core.nlp.datamodel.pos.ruscorpora.RuscorporaPOSTag">PUNCT</pos-tag>
                <characters class="java.util.ArrayList"/>
            </value>
        </I-annotation>
        <I-annotation confidence="1.0" class="ru.ispras.texterra.core.nlp.datamodel.pos.POSToken">
            <start>83</start>
            <end>84</end>
            <annotated-text reference="0"/>
            <value class="ru.ispras.texterra.core.nlp.datamodel.pos.morph.MorphProperties">
                <pos-tag class="ru.ispras.texterra.core.nlp.datamodel.pos.ruscorpora.RuscorporaPOSTag">CONJ</pos-tag>
                <characters class="java.util.ArrayList"/>
            </value>
        </I-annotation>
        <I-annotation confidence="1.0" class="ru.ispras.texterra.core.nlp.datamodel.pos.POSToken">
            <start>85</start>
            <end>92</end>
            <annotated-text reference="0"/>
            <value class="ru.ispras.texterra.core.nlp.datamodel.pos.morph.MorphProperties">
                <pos-tag class="ru.ispras.texterra.core.nlp.datamodel.pos.ruscorpora.RuscorporaPOSTag">S</pos-tag>
                <characters class="java.util.ArrayList">
                    <I-morph-character class="ru.ispras.texterra.core.nlp.datamodel.pos.morph.characters.Case">Nominative</I-morph-character>
                    <I-morph-character class="ru.ispras.texterra.core.nlp.datamodel.pos.morph.characters.Gender">Masculine</I-morph-character>
                    <I-morph-character class="ru.ispras.texterra.core.nlp.datamodel.pos.morph.characters.Number">Singular</I-morph-character>
                </characters>
            </value>
        </I-annotation>
        <I-annotation confidence="1.0" class="ru.ispras.texterra.core.nlp.datamodel.pos.POSToken">
            <start>93</start>
            <end>99</end>
            <annotated-text reference="0"/>
            <value class="ru.ispras.texterra.core.nlp.datamodel.pos.morph.MorphProperties">
                <pos-tag class="ru.ispras.texterra.core.nlp.datamodel.pos.ruscorpora.RuscorporaPOSTag">V</pos-tag>
                <characters class="java.util.ArrayList">
                    <I-morph-character class="ru.ispras.texterra.core.nlp.datamodel.pos.morph.characters.Gender">Masculine</I-morph-character>
                    <I-morph-character class="ru.ispras.texterra.core.nlp.datamodel.pos.morph.characters.Mode">Indicative</I-morph-character>
                    <I-morph-character class="ru.ispras.texterra.core.nlp.datamodel.pos.morph.characters.Number">Singular</I-morph-character>
                    <I-morph-character class="ru.ispras.texterra.core.nlp.datamodel.pos.morph.characters.Tense">Past</I-morph-character>
                </characters>
            </value>
        </I-annotation>
        <I-annotation confidence="1.0" class="ru.ispras.texterra.core.nlp.datamodel.pos.POSToken">
            <start>100</start>
            <end>102</end>
            <annotated-text reference="0"/>
            <value class="ru.ispras.texterra.core.nlp.datamodel.pos.morph.MorphProperties">
                <pos-tag class="ru.ispras.texterra.core.nlp.datamodel.pos.ruscorpora.RuscorporaPOSTag">S</pos-tag>
                <characters class="java.util.ArrayList">
                    <I-morph-character class="ru.ispras.texterra.core.nlp.datamodel.pos.morph.characters.Case">Genitive</I-morph-character>
                    <I-morph-character class="ru.ispras.texterra.core.nlp.datamodel.pos.morph.characters.Gender">Feminine</I-morph-character>
                    <I-morph-character class="ru.ispras.texterra.core.nlp.datamodel.pos.morph.characters.Number">Singular</I-morph-character>
                </characters>
            </value>
        </I-annotation>
        <I-annotation confidence="1.0" class="ru.ispras.texterra.core.nlp.datamodel.pos.POSToken">
            <start>103</start>
            <end>110</end>
            <annotated-text reference="0"/>
            <value class="ru.ispras.texterra.core.nlp.datamodel.pos.morph.MorphProperties">
                <pos-tag class="ru.ispras.texterra.core.nlp.datamodel.pos.ruscorpora.RuscorporaPOSTag">S</pos-tag>
                <characters class="java.util.ArrayList">
                    <I-morph-character class="ru.ispras.texterra.core.nlp.datamodel.pos.morph.characters.Case">Instrumental</I-morph-character>
                    <I-morph-character class="ru.ispras.texterra.core.nlp.datamodel.pos.morph.characters.Gender">Masculine</I-morph-character>
                    <I-morph-character class="ru.ispras.texterra.core.nlp.datamodel.pos.morph.characters.Number">Singular</I-morph-character>
                </characters>
            </value>
        </I-annotation>
    </annotations>
</NLP-document>